<?xml version="1.0" encoding="UTF-8" ?>
<!DOCTYPE mapper PUBLIC "-//mybatis.org//DTD Mapper 3.0//EN" "http://mybatis.org/dtd/mybatis-3-mapper.dtd" >
<mapper namespace="com.microblog.commment.dao.mapper.BlogCommentMapper" >
  <resultMap id="BaseResultMap" type="com.microblog.commment.dao.model.BlogComment" >
    <!--
      WARNING - @mbggenerated
      This element is automatically generated by MyBatis Generator, do not modify.
    -->
    <id column="id" property="id" jdbcType="BIGINT" />
    <result column="blog_id" property="blogId" jdbcType="BIGINT" />
    <result column="user_id" property="userId" jdbcType="BIGINT" />
    <result column="pid" property="pid" jdbcType="BIGINT" />
    <result column="reply_id" property="replyId" jdbcType="BIGINT" />
    <result column="publish_time" property="publishTime" jdbcType="TIMESTAMP" />
    <result column="content" property="content" jdbcType="LONGVARCHAR" />
  </resultMap>
  <delete id="deleteByPrimaryKey" parameterType="java.lang.Long" >
    <!--
      WARNING - @mbggenerated
      This element is automatically generated by MyBatis Generator, do not modify.
    -->
    delete from blog_comment
    where id = #{id,jdbcType=BIGINT}
  </delete>
  <insert id="insert" parameterType="com.microblog.commment.dao.model.BlogComment" >
    <!--
      WARNING - @mbggenerated
      This element is automatically generated by MyBatis Generator, do not modify.
    -->
    <selectKey resultType="java.lang.Long" keyProperty="id" order="AFTER" >
      SELECT LAST_INSERT_ID()
    </selectKey>
    insert into blog_comment (blog_id, user_id, pid, 
      reply_id, publish_time, content
      )
    values (#{blogId,jdbcType=BIGINT}, #{userId,jdbcType=BIGINT}, #{pid,jdbcType=BIGINT}, 
      #{replyId,jdbcType=BIGINT}, #{publishTime,jdbcType=TIMESTAMP}, #{content,jdbcType=LONGVARCHAR}
      )
  </insert>
  <update id="updateByPrimaryKey" parameterType="com.microblog.commment.dao.model.BlogComment" >
    <!--
      WARNING - @mbggenerated
      This element is automatically generated by MyBatis Generator, do not modify.
    -->
    update blog_comment
    set blog_id = #{blogId,jdbcType=BIGINT},
      user_id = #{userId,jdbcType=BIGINT},
      pid = #{pid,jdbcType=BIGINT},
      reply_id = #{replyId,jdbcType=BIGINT},
      publish_time = #{publishTime,jdbcType=TIMESTAMP},
      content = #{content,jdbcType=LONGVARCHAR}
    where id = #{id,jdbcType=BIGINT}
  </update>
  <select id="selectByPrimaryKey" resultMap="BaseResultMap" parameterType="java.lang.Long" >
    <!--
      WARNING - @mbggenerated
      This element is automatically generated by MyBatis Generator, do not modify.
    -->
    select id, blog_id, user_id, pid, reply_id, publish_time, content
    from blog_comment
    where id = #{id,jdbcType=BIGINT}
  </select>
  <select id="selectAll" resultMap="BaseResultMap" >
    <!--
      WARNING - @mbggenerated
      This element is automatically generated by MyBatis Generator, do not modify.
    -->
    select id, blog_id, user_id, pid, reply_id, publish_time, content
    from blog_comment
  </select>



  <select id="selectParent" resultMap="BaseResultMap" >
    select id, blog_id, user_id, pid, reply_id, publish_time, content
    from blog_comment
    where  blog_id = #{blogId} and reply_id = 0
    limit #{page},#{pageCount}
  </select>


  <select id="selectChild" resultMap="BaseResultMap" >
    select id, blog_id, user_id, pid, reply_id, publish_time, content
    from blog_comment
    where reply_id in
    <foreach item="item" index="index" collection="list" open="(" separator="," close=")">
      #{item}
    </foreach>
  </select>
</mapper>